{
"Abkhazia":"Абхазија",
"Albania":"Албанија",
"Afghanistan":"Авганистан",
"Alabama":"Алабама",
"Algeria":"Алжир",
"Algeria_Coast":"Алжир - Север",
"Algeria_Central":"Алжир - центар",
"Andorra":"Андора",
"Angola":"Ангола",
"Russia_Republic of Karelia_South Short":"Република Карелије",
"Russia_Republic of Karelia_North Short":"Република Карелије",
"Russia_Perm Krai_South Short":"Пермскиј крај",
"Spain_Castile and Leon_East Short":"Кастиља и Леон",
"Spain_Castile and Leon_West Short":"Кастиља и Леон",
"Switzerland_Espace Mittelland_East Short":"Еспаце Мителанд",
"Spain_Galicia_South Short":"Галиција",
"Spain_Galicia_North Short":"Галиција",
"Russia_Sverdlovsk Oblast_North Short":"Свердловска област",
"Azerbaijan":"Азербејџан",
"Argentina_Northwest":"Аргентински северозапад",
"Anguilla":"Ангвила",
"Antarctica":"Антарктик",
"Antigua and Barbuda":"Антигва и Барбуда",
"Argentina":"Аргентина",
"Argentina_Buenos Aires_South":"Провинција Буенос Аирес - Југ",
"Argentina_Cuyo":"Кујо",
"Argentina_Mesopotamia":"Месопотамија",
"Argentina_Pampas":"Пампас",
"Argentina_Patagonia":"Патагонија",
"Arizona":"Аризона",
"Armenia":"Јерменија",
"Australia":"Аустралија",
"Australia_Melbourne":"Мелбурн",
"Austria_Upper Austria":"Горња Аустрија",
"Austria_Vorarlberg":"Ворарлберг",
"Azerbaijan Region":"Азербејџан",
"Bahrain":"Бахреин",
"Bangladesh":"Бангладеш",
"Barbados":"Барбадос",
"Belarus":"Белорусија",
"Belarus_Brest Region":"Брестска област",
"Argentina_Buenos Aires_North":"Провинција Буенос Аирес - Север",
"Austria_Lower Austria_West Description":"Мостфиртел, Валдфиртел",
"Belarus_Hrodna Region":"Гродњенска област",
"Belarus_Maglieu Region":"Могиљовска област",
"Belarus_Homiel Region":"Гомељска област",
"Belarus_Vitebsk Region":"Витепска област",
"Belgium":"Белгија",
"Belarus_Minsk Region":"Минска област",
"Russia_Perm Krai":"Пермскиј крај",
"Russia_Republic of Karelia":"Република Карелије",
"Russia_Sverdlovsk Oblast":"Свердловска област",
"Spain_Galicia":"Галиција",
"Switzerland_Espace Mittelland":"Еспаце Мителанд",
"US_Pennsylvania_Reading":"Читање",
"Russia_Perm Krai_North Short":"Пермскиј крај",
"Spain_Castile and Leon":"Кастиља и Леон",
"People's Republic of China":"Кина",
"Taiwan":"Тајван",
"Australia_New South Wales":"Нови Јужни Велс",
"Australia_Northern Territory":"Северна Територија",
"Australia_Queensland":"Квинсленд",
"Australia_South Australia":"Јужна Аустралија",
"Australia_Tasmania":"Тасманија",
"Australia_Victoria":"Викторија",
"Austria":"Аустрија",
"Austria_Burgenland":"Бургенланд",
"Austria_Carinthia":"Корушка",
"Austria_Lower Austria_West":"Доња Аустрија — Запад",
"Austria_Salzburg":"Салцбург",
"Austria_Styria":"Штајерска",
"Austria_Tyrol":"Тирол",
"Belgium_Antwerp":"Антверпен",
"Belize":"Белизе",
"Benin":"Бенин",
"Bhutan":"Бутан",
"Bermuda":"Бермуди",
"Bolivia":"Боливија",
"Bolivia_North":"Боливија – Сервер",
"Bolivia_South":"Боливија – Југ",
"Bosnia and Herzegovina":"Босна и Херцеговина",
"Bosnia and Herzegovina_Brcko district of Bosnia and Herzegowina":"Брчко",
"Bosnia and Herzegovina_Entity Federation of Bosnia and Herzegovina":"Федерација Босне и Херцеговине",
"Bosnia and Herzegovina_Republic of Srpska":"Република Српска",
"Botswana":"Боцвана",
"Brazil":"Бразил",
"Brazil_Bahia":"Баија",
"Brunei":"Брунеј",
"Bulgaria":"Бугарска",
"Burkina Faso":"Буркина Фасо",
"Burundi":"Бурунди",
"California":"Калифорнија",
"Cambodia":"Камбоџа",
"Cameroon":"Камерун",
"Cameroon_Central":"Камерун — Центар",
"Cameroon_West":"Камерун — Запад",
"Canada":"Канада",
"Canada_Alberta":"Алберта",
"Canada_Alberta_Edmonton":"Едмонтон",
"Canada_Alberta_North":"Алберта — Сервер",
"Canada_British Columbia":"Британска Колумбија",
"Australia_Western Australia":"Западна Аустралија",
"Austria_Lower Austria_Wien":"Беч и Доња Аустрија — Исток",
"Belgium_East Flanders":"Источна Фландрија",
"Canada_Alberta_South":"Алберта — Југ"
}
